{
    "type": "bundle",
    "id": "bundle--e8d6c30c-90bf-4687-a8db-b5b6a56733e2",
    "objects": [
        {
            "type": "relationship",
            "spec_version": "2.1",
            "id": "relationship--d853ae09-869e-4e19-9217-e7e4a870b840",
            "created_by_ref": "identity--b73c59c1-8560-449a-b8d0-c2ce0533c5bf",
            "created": "2023-09-27T14:45:12.485284Z",
            "modified": "2023-09-27T14:45:12.485284Z",
            "relationship_type": "uses",
            "description": "Defense Evasion::Install Insecure or Malicious Configuration (B0047) -- Malware configures the system to the TESTSIGNING boot configuration option to load its unsigned driver component. [1]",
            "source_ref": "malware--2bf9105d-5791-4e25-b231-944dc7ec724f",
            "target_ref": "malware-behavior--f252b047-4d2a-4eab-bf7f-bd36427fb08a",
            "object_marking_refs": [
                "marking-definition--093b6375-cd45-4aa3-8f91-6a03ddd7a3d3"
            ]
        }
    ]
}